py_pkpass/__init__.py
py_pkpass/models.py
py_pkpass/test/__init__.py
py_pkpass/test/test_advanced_features.py
py_pkpass/test/test_pass_types.py
py_pkpass/test/test_passbook.py
py_pkpass/test/test_signature.py
py_pkpass-1.0.2.dist-info/licenses/LICENSE.txt
py_pkpass-1.0.2.dist-info/METADATA
py_pkpass-1.0.2.dist-info/WHEEL
py_pkpass-1.0.2.dist-info/top_level.txt
py_pkpass-1.0.2.dist-info/RECORD
