Metadata-Version: 2.4
Name: py-pkpass
Version: 1.0.2
Summary: Pkpass file generator
Home-page: https://github.com/GlitchOo/py-pkpass/
Download-URL: https://github.com/GlitchOo/py-pkpass/archive/refs/tags/v1.0.2.tar.gz
Author: GlitchOo
License: The MIT License (MIT)
Classifier: Development Status :: 3 - Alpha
Classifier: Environment :: Other Environment
Classifier: Intended Audience :: Developers
Classifier: Programming Language :: Python :: 3.8
Classifier: Programming Language :: Python :: 3 :: Only
Classifier: Topic :: Software Development :: Libraries :: Python Modules
License-File: LICENSE.txt
Requires-Dist: cryptography>=44.0.1
Requires-Dist: swig; python_version >= "3.10"
Dynamic: author
Dynamic: classifier
Dynamic: description
Dynamic: description-content-type
Dynamic: download-url
Dynamic: home-page
Dynamic: license
Dynamic: license-file
Dynamic: provides-extra
Dynamic: requires-dist
Dynamic: summary
